{
  "uid": "tiresias-prometheus",
  "title": "Prometheus Health",
  "tags": ["prometheus", "tiresias", "monitoring"],
  "timezone": "browser",
  "schemaVersion": 39,
  "version": 1,
  "refresh": "30s",
  "editable": true,
  "fiscalYearStartMonth": 0,
  "graphTooltip": 1,
  "time": {
    "from": "now-1h",
    "to": "now"
  },
  "templating": {
    "list": []
  },
  "annotations": {
    "list": [
      {
        "builtIn": 1,
        "datasource": { "type": "grafana", "uid": "-- Grafana --" },
        "enable": true,
        "hide": true,
        "iconColor": "rgba(0, 211, 255, 1)",
        "name": "Annotations & Alerts",
        "type": "dashboard"
      }
    ]
  },
  "panels": [
    {
      "id": 1,
      "title": "Active Targets",
      "type": "stat",
      "gridPos": { "h": 3, "w": 4, "x": 0, "y": 0 },
      "datasource": { "type": "prometheus", "uid": "prometheus" },
      "targets": [
        {
          "refId": "A",
          "expr": "count(up)",
          "instant": true
        }
      ],
      "fieldConfig": {
        "defaults": {
          "thresholds": {
            "mode": "absolute",
            "steps": [
              { "color": "blue", "value": null }
            ]
          },
          "color": { "mode": "thresholds" }
        },
        "overrides": []
      },
      "options": {
        "reduceOptions": {
          "calcs": ["lastNotNull"],
          "fields": "",
          "values": false
        },
        "textMode": "auto",
        "colorMode": "value",
        "graphMode": "none",
        "justifyMode": "auto",
        "orientation": "auto"
      }
    },
    {
      "id": 2,
      "title": "Targets Up",
      "type": "stat",
      "gridPos": { "h": 3, "w": 4, "x": 4, "y": 0 },
      "datasource": { "type": "prometheus", "uid": "prometheus" },
      "targets": [
        {
          "refId": "A",
          "expr": "count(up == 1)",
          "instant": true
        }
      ],
      "fieldConfig": {
        "defaults": {
          "thresholds": {
            "mode": "absolute",
            "steps": [
              { "color": "green", "value": null }
            ]
          },
          "color": { "mode": "thresholds" }
        },
        "overrides": []
      },
      "options": {
        "reduceOptions": {
          "calcs": ["lastNotNull"],
          "fields": "",
          "values": false
        },
        "textMode": "auto",
        "colorMode": "value",
        "graphMode": "none",
        "justifyMode": "auto",
        "orientation": "auto"
      }
    },
    {
      "id": 3,
      "title": "Targets Down",
      "type": "stat",
      "gridPos": { "h": 3, "w": 4, "x": 8, "y": 0 },
      "datasource": { "type": "prometheus", "uid": "prometheus" },
      "targets": [
        {
          "refId": "A",
          "expr": "count(up == 0) OR on() vector(0)",
          "instant": true
        }
      ],
      "fieldConfig": {
        "defaults": {
          "thresholds": {
            "mode": "absolute",
            "steps": [
              { "color": "green", "value": null },
              { "color": "red", "value": 1 }
            ]
          },
          "color": { "mode": "thresholds" }
        },
        "overrides": []
      },
      "options": {
        "reduceOptions": {
          "calcs": ["lastNotNull"],
          "fields": "",
          "values": false
        },
        "textMode": "auto",
        "colorMode": "value",
        "graphMode": "none",
        "justifyMode": "auto",
        "orientation": "auto"
      }
    },
    {
      "id": 4,
      "title": "Scrape Duration (avg)",
      "type": "stat",
      "gridPos": { "h": 3, "w": 4, "x": 12, "y": 0 },
      "datasource": { "type": "prometheus", "uid": "prometheus" },
      "targets": [
        {
          "refId": "A",
          "expr": "avg(scrape_duration_seconds)",
          "instant": true
        }
      ],
      "fieldConfig": {
        "defaults": {
          "unit": "s",
          "thresholds": {
            "mode": "absolute",
            "steps": [
              { "color": "green", "value": null },
              { "color": "yellow", "value": 1 },
              { "color": "red", "value": 5 }
            ]
          },
          "color": { "mode": "thresholds" }
        },
        "overrides": []
      },
      "options": {
        "reduceOptions": {
          "calcs": ["lastNotNull"],
          "fields": "",
          "values": false
        },
        "textMode": "auto",
        "colorMode": "value",
        "graphMode": "none",
        "justifyMode": "auto",
        "orientation": "auto"
      }
    },
    {
      "id": 5,
      "title": "TSDB Head Series",
      "type": "stat",
      "gridPos": { "h": 3, "w": 4, "x": 16, "y": 0 },
      "datasource": { "type": "prometheus", "uid": "prometheus" },
      "targets": [
        {
          "refId": "A",
          "expr": "prometheus_tsdb_head_series",
          "instant": true
        }
      ],
      "fieldConfig": {
        "defaults": {
          "thresholds": {
            "mode": "absolute",
            "steps": [
              { "color": "blue", "value": null }
            ]
          },
          "color": { "mode": "thresholds" }
        },
        "overrides": []
      },
      "options": {
        "reduceOptions": {
          "calcs": ["lastNotNull"],
          "fields": "",
          "values": false
        },
        "textMode": "auto",
        "colorMode": "value",
        "graphMode": "none",
        "justifyMode": "auto",
        "orientation": "auto"
      }
    },
    {
      "id": 6,
      "title": "TSDB Storage Size",
      "type": "stat",
      "gridPos": { "h": 3, "w": 4, "x": 20, "y": 0 },
      "datasource": { "type": "prometheus", "uid": "prometheus" },
      "targets": [
        {
          "refId": "A",
          "expr": "prometheus_tsdb_storage_size_bytes",
          "instant": true
        }
      ],
      "fieldConfig": {
        "defaults": {
          "unit": "bytes",
          "thresholds": {
            "mode": "absolute",
            "steps": [
              { "color": "blue", "value": null }
            ]
          },
          "color": { "mode": "thresholds" }
        },
        "overrides": []
      },
      "options": {
        "reduceOptions": {
          "calcs": ["lastNotNull"],
          "fields": "",
          "values": false
        },
        "textMode": "auto",
        "colorMode": "value",
        "graphMode": "none",
        "justifyMode": "auto",
        "orientation": "auto"
      }
    },
    {
      "id": 7,
      "title": "Target Status",
      "type": "table",
      "gridPos": { "h": 7, "w": 12, "x": 0, "y": 3 },
      "datasource": { "type": "prometheus", "uid": "prometheus" },
      "targets": [
        {
          "refId": "A",
          "expr": "up",
          "instant": true,
          "format": "table"
        }
      ],
      "fieldConfig": {
        "defaults": {},
        "overrides": [
          {
            "matcher": { "id": "byName", "options": "Value" },
            "properties": [
              {
                "id": "mappings",
                "value": [
                  {
                    "type": "value",
                    "options": {
                      "0": { "text": "DOWN", "color": "red" },
                      "1": { "text": "UP", "color": "green" }
                    }
                  }
                ]
              },
              {
                "id": "custom.cellOptions",
                "value": {
                  "type": "color-background",
                  "mode": "basic"
                }
              }
            ]
          }
        ]
      },
      "options": {
        "showHeader": true,
        "cellHeight": "sm",
        "footer": {
          "show": false,
          "reducer": ["sum"],
          "countRows": false
        }
      },
      "transformations": [
        {
          "id": "organize",
          "options": {
            "excludeByName": {
              "Time": true,
              "__name__": true
            },
            "indexByName": {},
            "renameByName": {},
            "includeByName": {
              "job": true,
              "instance": true,
              "Value": true
            }
          }
        }
      ]
    },
    {
      "id": 8,
      "title": "Scrape Duration by Job",
      "type": "timeseries",
      "gridPos": { "h": 7, "w": 12, "x": 12, "y": 3 },
      "datasource": { "type": "prometheus", "uid": "prometheus" },
      "targets": [
        {
          "refId": "A",
          "expr": "scrape_duration_seconds",
          "legendFormat": "{{job}}"
        }
      ],
      "fieldConfig": {
        "defaults": {
          "unit": "s",
          "color": { "mode": "palette-classic" },
          "custom": {
            "drawStyle": "line",
            "lineInterpolation": "smooth",
            "lineWidth": 2,
            "fillOpacity": 10,
            "gradientMode": "none",
            "spanNulls": false,
            "showPoints": "auto",
            "pointSize": 5,
            "stacking": { "mode": "none", "group": "A" },
            "axisPlacement": "auto",
            "axisBorderShow": false,
            "scaleDistribution": { "type": "linear" },
            "thresholdsStyle": { "mode": "off" }
          },
          "thresholds": {
            "mode": "absolute",
            "steps": [
              { "color": "green", "value": null }
            ]
          }
        },
        "overrides": []
      },
      "options": {
        "tooltip": { "mode": "multi", "sort": "desc" },
        "legend": { "displayMode": "list", "placement": "bottom", "calcs": [] }
      }
    },
    {
      "id": 9,
      "title": "Samples Ingested",
      "type": "timeseries",
      "gridPos": { "h": 7, "w": 12, "x": 0, "y": 10 },
      "datasource": { "type": "prometheus", "uid": "prometheus" },
      "targets": [
        {
          "refId": "A",
          "expr": "rate(prometheus_tsdb_head_samples_appended_total[5m])",
          "legendFormat": "Samples/s"
        }
      ],
      "fieldConfig": {
        "defaults": {
          "color": { "mode": "palette-classic" },
          "custom": {
            "drawStyle": "line",
            "lineInterpolation": "smooth",
            "lineWidth": 2,
            "fillOpacity": 10,
            "gradientMode": "none",
            "spanNulls": false,
            "showPoints": "auto",
            "pointSize": 5,
            "stacking": { "mode": "none", "group": "A" },
            "axisPlacement": "auto",
            "axisBorderShow": false,
            "scaleDistribution": { "type": "linear" },
            "thresholdsStyle": { "mode": "off" }
          },
          "thresholds": {
            "mode": "absolute",
            "steps": [
              { "color": "green", "value": null }
            ]
          }
        },
        "overrides": []
      },
      "options": {
        "tooltip": { "mode": "multi", "sort": "desc" },
        "legend": { "displayMode": "list", "placement": "bottom", "calcs": [] }
      }
    },
    {
      "id": 10,
      "title": "Head Chunks",
      "type": "timeseries",
      "gridPos": { "h": 7, "w": 12, "x": 12, "y": 10 },
      "datasource": { "type": "prometheus", "uid": "prometheus" },
      "targets": [
        {
          "refId": "A",
          "expr": "prometheus_tsdb_head_chunks",
          "legendFormat": "Chunks"
        }
      ],
      "fieldConfig": {
        "defaults": {
          "color": { "mode": "palette-classic" },
          "custom": {
            "drawStyle": "line",
            "lineInterpolation": "smooth",
            "lineWidth": 2,
            "fillOpacity": 10,
            "gradientMode": "none",
            "spanNulls": false,
            "showPoints": "auto",
            "pointSize": 5,
            "stacking": { "mode": "none", "group": "A" },
            "axisPlacement": "auto",
            "axisBorderShow": false,
            "scaleDistribution": { "type": "linear" },
            "thresholdsStyle": { "mode": "off" }
          },
          "thresholds": {
            "mode": "absolute",
            "steps": [
              { "color": "green", "value": null }
            ]
          }
        },
        "overrides": []
      },
      "options": {
        "tooltip": { "mode": "multi", "sort": "desc" },
        "legend": { "displayMode": "list", "placement": "bottom", "calcs": [] }
      }
    },
    {
      "id": 11,
      "title": "TSDB Compactions",
      "type": "timeseries",
      "gridPos": { "h": 7, "w": 12, "x": 0, "y": 17 },
      "datasource": { "type": "prometheus", "uid": "prometheus" },
      "targets": [
        {
          "refId": "A",
          "expr": "rate(prometheus_tsdb_compactions_total[5m])",
          "legendFormat": "Compactions/s"
        }
      ],
      "fieldConfig": {
        "defaults": {
          "color": { "mode": "palette-classic" },
          "custom": {
            "drawStyle": "line",
            "lineInterpolation": "smooth",
            "lineWidth": 2,
            "fillOpacity": 10,
            "gradientMode": "none",
            "spanNulls": false,
            "showPoints": "auto",
            "pointSize": 5,
            "stacking": { "mode": "none", "group": "A" },
            "axisPlacement": "auto",
            "axisBorderShow": false,
            "scaleDistribution": { "type": "linear" },
            "thresholdsStyle": { "mode": "off" }
          },
          "thresholds": {
            "mode": "absolute",
            "steps": [
              { "color": "green", "value": null }
            ]
          }
        },
        "overrides": []
      },
      "options": {
        "tooltip": { "mode": "multi", "sort": "desc" },
        "legend": { "displayMode": "list", "placement": "bottom", "calcs": [] }
      }
    },
    {
      "id": 12,
      "title": "Query Duration",
      "type": "timeseries",
      "gridPos": { "h": 7, "w": 12, "x": 12, "y": 17 },
      "datasource": { "type": "prometheus", "uid": "prometheus" },
      "targets": [
        {
          "refId": "A",
          "expr": "rate(prometheus_engine_query_duration_seconds_sum[5m]) / rate(prometheus_engine_query_duration_seconds_count[5m])",
          "legendFormat": "{{slice}}"
        }
      ],
      "fieldConfig": {
        "defaults": {
          "unit": "s",
          "color": { "mode": "palette-classic" },
          "custom": {
            "drawStyle": "line",
            "lineInterpolation": "smooth",
            "lineWidth": 2,
            "fillOpacity": 10,
            "gradientMode": "none",
            "spanNulls": false,
            "showPoints": "auto",
            "pointSize": 5,
            "stacking": { "mode": "none", "group": "A" },
            "axisPlacement": "auto",
            "axisBorderShow": false,
            "scaleDistribution": { "type": "linear" },
            "thresholdsStyle": { "mode": "off" }
          },
          "thresholds": {
            "mode": "absolute",
            "steps": [
              { "color": "green", "value": null }
            ]
          }
        },
        "overrides": []
      },
      "options": {
        "tooltip": { "mode": "multi", "sort": "desc" },
        "legend": { "displayMode": "list", "placement": "bottom", "calcs": [] }
      }
    },
    {
      "id": 13,
      "title": "Rule Evaluation Duration",
      "type": "timeseries",
      "gridPos": { "h": 7, "w": 12, "x": 0, "y": 24 },
      "datasource": { "type": "prometheus", "uid": "prometheus" },
      "targets": [
        {
          "refId": "A",
          "expr": "rate(prometheus_rule_evaluation_duration_seconds_sum[5m])",
          "legendFormat": "Rule Eval Duration"
        }
      ],
      "fieldConfig": {
        "defaults": {
          "unit": "s",
          "color": { "mode": "palette-classic" },
          "custom": {
            "drawStyle": "line",
            "lineInterpolation": "smooth",
            "lineWidth": 2,
            "fillOpacity": 10,
            "gradientMode": "none",
            "spanNulls": false,
            "showPoints": "auto",
            "pointSize": 5,
            "stacking": { "mode": "none", "group": "A" },
            "axisPlacement": "auto",
            "axisBorderShow": false,
            "scaleDistribution": { "type": "linear" },
            "thresholdsStyle": { "mode": "off" }
          },
          "thresholds": {
            "mode": "absolute",
            "steps": [
              { "color": "green", "value": null }
            ]
          }
        },
        "overrides": []
      },
      "options": {
        "tooltip": { "mode": "multi", "sort": "desc" },
        "legend": { "displayMode": "list", "placement": "bottom", "calcs": [] }
      }
    },
    {
      "id": 14,
      "title": "Alerts",
      "type": "stat",
      "gridPos": { "h": 7, "w": 12, "x": 12, "y": 24 },
      "datasource": { "type": "prometheus", "uid": "prometheus" },
      "targets": [
        {
          "refId": "A",
          "expr": "ALERTS{alertstate=\"firing\"}",
          "legendFormat": "{{alertname}}",
          "instant": true
        }
      ],
      "fieldConfig": {
        "defaults": {
          "thresholds": {
            "mode": "absolute",
            "steps": [
              { "color": "green", "value": null },
              { "color": "orange", "value": 1 }
            ]
          },
          "color": { "mode": "thresholds" }
        },
        "overrides": []
      },
      "options": {
        "reduceOptions": {
          "calcs": ["lastNotNull"],
          "fields": "",
          "values": false
        },
        "textMode": "auto",
        "colorMode": "value",
        "graphMode": "none",
        "justifyMode": "auto",
        "orientation": "auto"
      }
    }
  ]
}